simple_elmo_pytorch/__init__.py
simple_elmo_pytorch/checks.py
simple_elmo_pytorch/file_utils.py
simple_elmo_pytorch/util.py
simple_elmo_pytorch/data/__init__.py
simple_elmo_pytorch/data/batch.py
simple_elmo_pytorch/data/elmo_indexer.py
simple_elmo_pytorch/data/fields.py
simple_elmo_pytorch/data/instance.py
simple_elmo_pytorch/data/token_indexers.py
simple_elmo_pytorch/data/tokenizers.py
simple_elmo_pytorch/data/vocabulary.py
simple_elmo_pytorch/models/__init__.py
simple_elmo_pytorch/models/elmo.py
simple_elmo_pytorch/models/elmo_lstm.py
simple_elmo_pytorch/models/elmo_vectorize.py
simple_elmo_pytorch/models/encoder_base.py
simple_elmo_pytorch/models/highway.py
simple_elmo_pytorch/models/lstm_cell_with_projection.py
simple_elmo_pytorch/models/scalar_mix.py
simple_elmo_pytorch/models/token_embedders.py
simple_elmo_pytorch/nn/__init__.py
simple_elmo_pytorch/nn/initializers.py
simple_elmo_pytorch/nn/util.py
simple_elmo_pytorch-0.2.dist-info/METADATA
simple_elmo_pytorch-0.2.dist-info/WHEEL
simple_elmo_pytorch-0.2.dist-info/top_level.txt
simple_elmo_pytorch-0.2.dist-info/RECORD
