Metadata-Version: 2.1
Name: simple-elmo-pytorch
Version: 0.2
Summary: Simple_elmo pytorch is a Python library to work with pre-trained ELMo embeddings in PyTorch
Author-email: joefox@inbox.ru
